[
	{"op": "replace", "path": "/metadata/labels", "value": "querycdncontents"},
	{"op": "replace", "path": "/metadata/name", "value": "querycdncontents"},
	{"op": "replace", "path": "/spec/selector/matchLabels/faas_function", "value": "querycdncontents"},
	{"op": "replace", "path": "/spec/template/metadata/labels", "value": "querycdncontents"},
	{"op": "replace", "path": "/spec/template/metadata/name", "value": "querycdncontents"},
	{"op": "replace", "path": "/spec/template/spec/containers/0/name", "value": "querycdncontents"},
	{"op": "replace", "path": "/spec/template/spec/containers/0/volumeMounts/0/name", "value": "querycdncontents-projected-secrets"},
	{"op": "replace", "path": "/spec/template/spec/volumes/0/name", "value": "querycdncontents-projected-secrets"}
]
